libs/__init__.py
libs/csmxhashlib.py
libs/csmxos.py
libs/csmxrandom.py
libs/csmxsecrets.py
libs/csmxsys.py
src/__init__.py
src/csmxnet.py
tests/__init__.py
tests/test_csmxnet.py
csmxnet-1.0.0.dist-info/METADATA
csmxnet-1.0.0.dist-info/WHEEL
csmxnet-1.0.0.dist-info/top_level.txt
csmxnet-1.0.0.dist-info/RECORD
